{"26b60d1bbea0eacb94544899fb68cc5f":{"statistic":{"failed":1,"broken":0,"skipped":0,"passed":0,"unknown":0,"total":1},"items":[{"uid":"792a2deaf690ac83","reportUrl":"https://itdelta-agency.github.io/op3-cypress-tests/75//#testresult/792a2deaf690ac83","status":"failed","statusDetails":"`cy.click()` can only be called on a single element. Your subject contained 2 elements. Pass `{ multiple: true }` if you want to serially click each element.\n\nhttps://on.cypress.io/click","time":{"start":1668071265032,"stop":1668071276515,"duration":11483}}]},"49568977778b423f92dab054ca593093":{"statistic":{"failed":0,"broken":0,"skipped":0,"passed":1,"unknown":0,"total":1},"items":[{"uid":"d4403ba16ad26a6","reportUrl":"https://itdelta-agency.github.io/op3-cypress-tests/75//#testresult/d4403ba16ad26a6","status":"passed","time":{"start":1668071015834,"stop":1668071028821,"duration":12987}}]},"347a6abd1f9bd42196dbd1a0c29d1d61":{"statistic":{"failed":0,"broken":0,"skipped":0,"passed":1,"unknown":0,"total":1},"items":[{"uid":"788a8e317d896fe","reportUrl":"https://itdelta-agency.github.io/op3-cypress-tests/75//#testresult/788a8e317d896fe","status":"passed","time":{"start":1668071250101,"stop":1668071265024,"duration":14923}}]},"f8a62f3aa99bd0766fcc494238225cd4":{"statistic":{"failed":1,"broken":0,"skipped":0,"passed":0,"unknown":0,"total":1},"items":[{"uid":"befaed0d7a7f4e17","reportUrl":"https://itdelta-agency.github.io/op3-cypress-tests/75//#testresult/befaed0d7a7f4e17","status":"failed","statusDetails":"Timed out retrying after 30000ms: Expected to find element: `//div[text()='QA DON T TOUCH']`, but never found it.","time":{"start":1668071144121,"stop":1668071179825,"duration":35704}}]},"ac3588a0622880cedd35cc5ae7fbf2cf":{"statistic":{"failed":0,"broken":0,"skipped":0,"passed":1,"unknown":0,"total":1},"items":[{"uid":"d0ad4e08d473131c","reportUrl":"https://itdelta-agency.github.io/op3-cypress-tests/75//#testresult/d0ad4e08d473131c","status":"passed","time":{"start":1668070949779,"stop":1668070971536,"duration":21757}}]},"738e05887ac1c092e637f9ae3bc4131d":{"statistic":{"failed":0,"broken":0,"skipped":0,"passed":1,"unknown":0,"total":1},"items":[{"uid":"3b69cdd8e12552fe","reportUrl":"https://itdelta-agency.github.io/op3-cypress-tests/75//#testresult/3b69cdd8e12552fe","status":"passed","time":{"start":1668070914605,"stop":1668070949729,"duration":35124}}]},"c47154a18e030bf825e67ace1a9d77f6":{"statistic":{"failed":1,"broken":0,"skipped":0,"passed":0,"unknown":0,"total":1},"items":[{"uid":"5f680fdc683fa4b2","reportUrl":"https://itdelta-agency.github.io/op3-cypress-tests/75//#testresult/5f680fdc683fa4b2","status":"failed","statusDetails":"Cypress detected a cross origin error happened on page load:\n\n  > Blocked a frame with origin \"https://itdelta.learn.company-policy.com\" from accessing a cross-origin frame.\n\nBefore the page load, you were bound to the origin:\n\n  > https://itdelta.learn.company-policy.com\n\nA cross origin error happens when your application navigates to a new URL which does not match the origin above.\n\nA new URL does not match the origin if the 'protocol', 'port' (if specified), and/or 'host' are different.\n\nCypress does not allow you to navigate to a different origin URL within a single test.\n\nYou may need to restructure some of your test code to avoid this problem.\n\nAlternatively you can also disable Chrome Web Security in Chromium-based browsers which will turn off this restriction by setting { chromeWebSecurity: false } in `home/runner/work/op3-cypress-tests/op3-cypress-tests/cypress.config.js`.\n\nhttps://on.cypress.io/cross-origin-violation","time":{"start":1668070841474,"stop":1668070847428,"duration":5954}}]},"713c902c43dacb49a9c818fe1593a785":{"statistic":{"failed":0,"broken":0,"skipped":0,"passed":1,"unknown":0,"total":1},"items":[{"uid":"f9fa21921ad2489e","reportUrl":"https://itdelta-agency.github.io/op3-cypress-tests/75//#testresult/f9fa21921ad2489e","status":"passed","time":{"start":1668071051628,"stop":1668071063708,"duration":12080}}]},"0783d8d5afddf6ffa07a490362a192f5":{"statistic":{"failed":0,"broken":0,"skipped":0,"passed":1,"unknown":0,"total":1},"items":[{"uid":"173d52251314b334","reportUrl":"https://itdelta-agency.github.io/op3-cypress-tests/75//#testresult/173d52251314b334","status":"passed","time":{"start":1668071126017,"stop":1668071129795,"duration":3778}}]},"535aa4a445314e8a8f5dbb5226b1ad88":{"statistic":{"failed":1,"broken":0,"skipped":0,"passed":0,"unknown":0,"total":1},"items":[{"uid":"34f36834ba8c4634","reportUrl":"https://itdelta-agency.github.io/op3-cypress-tests/75//#testresult/34f36834ba8c4634","status":"failed","statusDetails":"Timed out retrying after 5000ms: Expected to find element: `//p[text()='Success!']`, but never found it.","time":{"start":1668070982550,"stop":1668070994384,"duration":11834}}]},"09a7952d62c436a10cf66fa58e2def33":{"statistic":{"failed":0,"broken":0,"skipped":0,"passed":1,"unknown":0,"total":1},"items":[{"uid":"c7a38d4499869aef","reportUrl":"https://itdelta-agency.github.io/op3-cypress-tests/75//#testresult/c7a38d4499869aef","status":"passed","time":{"start":1668070828032,"stop":1668070832210,"duration":4178}}]},"49e2b9a4b7c04427525f670a1736707a":{"statistic":{"failed":0,"broken":0,"skipped":0,"passed":1,"unknown":0,"total":1},"items":[{"uid":"e3d01a38be90662f","reportUrl":"https://itdelta-agency.github.io/op3-cypress-tests/75//#testresult/e3d01a38be90662f","status":"passed","time":{"start":1668070998449,"stop":1668071011512,"duration":13063}}]},"ae2aa8e8f78a9fb232b1ff9e19e56f31":{"statistic":{"failed":0,"broken":0,"skipped":0,"passed":1,"unknown":0,"total":1},"items":[{"uid":"feeeadeab9e8cbd5","reportUrl":"https://itdelta-agency.github.io/op3-cypress-tests/75//#testresult/feeeadeab9e8cbd5","status":"passed","time":{"start":1668071119176,"stop":1668071122013,"duration":2837}}]},"4be1ef711e8a946fcf220a21eaf5908a":{"statistic":{"failed":1,"broken":0,"skipped":0,"passed":0,"unknown":0,"total":1},"items":[{"uid":"5a24a7486b92b919","reportUrl":"https://itdelta-agency.github.io/op3-cypress-tests/75//#testresult/5a24a7486b92b919","status":"failed","statusDetails":"Timed out retrying after 5000ms: Expected to find element: `//p[text()='Success!']`, but never found it.","time":{"start":1668070854362,"stop":1668070867072,"duration":12710}}]},"80ac23c37267f471feb0a2b854422a1d":{"statistic":{"failed":0,"broken":0,"skipped":0,"passed":1,"unknown":0,"total":1},"items":[{"uid":"8263fbb370400c14","reportUrl":"https://itdelta-agency.github.io/op3-cypress-tests/75//#testresult/8263fbb370400c14","status":"passed","time":{"start":1668071122023,"stop":1668071126010,"duration":3987}}]},"5951b2828c25c4fe4ca6d9300109bb30":{"statistic":{"failed":0,"broken":0,"skipped":0,"passed":1,"unknown":0,"total":1},"items":[{"uid":"fca490b4ffd3086b","reportUrl":"https://itdelta-agency.github.io/op3-cypress-tests/75//#testresult/fca490b4ffd3086b","status":"passed","time":{"start":1668071229751,"stop":1668071250072,"duration":20321}}]},"808cadf0ce1884b002494914fd4b662f":{"statistic":{"failed":0,"broken":0,"skipped":0,"passed":1,"unknown":0,"total":1},"items":[{"uid":"5ce461c1ae6c0e21","reportUrl":"https://itdelta-agency.github.io/op3-cypress-tests/75//#testresult/5ce461c1ae6c0e21","status":"passed","time":{"start":1668071033032,"stop":1668071047184,"duration":14152}}]},"c6984a94140a7fcd549ce403863b8975":{"statistic":{"failed":1,"broken":0,"skipped":0,"passed":0,"unknown":0,"total":1},"items":[{"uid":"4e976a05d93b07a0","reportUrl":"https://itdelta-agency.github.io/op3-cypress-tests/75//#testresult/4e976a05d93b07a0","status":"failed","statusDetails":"Timed out retrying after 30000ms: Expected to find element: `//div[text()='Lesson successfully completed!']`, but never found it.","time":{"start":1668071191657,"stop":1668071222998,"duration":31341}}]},"ca469ac9b46b80c82ecf26927352e821":{"statistic":{"failed":1,"broken":0,"skipped":0,"passed":0,"unknown":0,"total":1},"items":[{"uid":"f80e400ef51be5ad","reportUrl":"https://itdelta-agency.github.io/op3-cypress-tests/75//#testresult/f80e400ef51be5ad","status":"failed","statusDetails":"`cy.task('getLastEmail')` failed with the following error:\n\n> Cannot read properties of undefined (reading 'toString')\n\nhttps://on.cypress.io/api/task","time":{"start":1668070847471,"stop":1668070850453,"duration":2982}}]},"8efa7b1ba7594d8b34b0455f343b549e":{"statistic":{"failed":1,"broken":0,"skipped":0,"passed":0,"unknown":0,"total":1},"items":[{"uid":"cea0b7fb05c7b53","reportUrl":"https://itdelta-agency.github.io/op3-cypress-tests/75//#testresult/cea0b7fb05c7b53","status":"failed","statusDetails":"Timed out retrying after 30000ms: Expected to find element: `//h1[text()='QA Test lesson (text)']`, but never found it.","time":{"start":1668071071422,"stop":1668071105988,"duration":34566}}]},"575f4dd91c34f6f9bb06195f09b1c2a1":{"statistic":{"failed":1,"broken":0,"skipped":0,"passed":0,"unknown":0,"total":1},"items":[{"uid":"d2995be66e3e86f1","reportUrl":"https://itdelta-agency.github.io/op3-cypress-tests/75//#testresult/d2995be66e3e86f1","status":"failed","statusDetails":"`cy.click()` can only be called on a single element. Your subject contained 2 elements. Pass `{ multiple: true }` if you want to serially click each element.\n\nhttps://on.cypress.io/click","time":{"start":1668071276539,"stop":1668071288196,"duration":11657}}]},"28af254968efcc394ed806d8e4b5df9f":{"statistic":{"failed":1,"broken":0,"skipped":0,"passed":0,"unknown":0,"total":1},"items":[{"uid":"c59fde3b7cb2a6e1","reportUrl":"https://itdelta-agency.github.io/op3-cypress-tests/75//#testresult/c59fde3b7cb2a6e1","status":"failed","statusDetails":"`cy.visit()` must be called with a `url` or an `options` object containing a `url` as its 1st argument\n\nhttps://on.cypress.io/visit","time":{"start":1668070867099,"stop":1668070877309,"duration":10210}}]},"f82ab1cd41f023abc7c907f95fa8f17d":{"statistic":{"failed":0,"broken":0,"skipped":0,"passed":1,"unknown":0,"total":1},"items":[{"uid":"7ff1893719fc0624","reportUrl":"https://itdelta-agency.github.io/op3-cypress-tests/75//#testresult/7ff1893719fc0624","status":"passed","time":{"start":1668070877358,"stop":1668070889842,"duration":12484}}]},"f7fbd7be243570c93dbb4b5bd88b0c15":{"statistic":{"failed":0,"broken":0,"skipped":0,"passed":1,"unknown":0,"total":1},"items":[{"uid":"819e42684bd73339","reportUrl":"https://itdelta-agency.github.io/op3-cypress-tests/75//#testresult/819e42684bd73339","status":"passed","time":{"start":1668070832243,"stop":1668070836205,"duration":3962}}]},"c74b31718cc46f4ce948e3f30c613343":{"statistic":{"failed":1,"broken":0,"skipped":0,"passed":0,"unknown":0,"total":1},"items":[{"uid":"d2202cd054154755","reportUrl":"https://itdelta-agency.github.io/op3-cypress-tests/75//#testresult/d2202cd054154755","status":"failed","statusDetails":"Timed out retrying after 5000ms: Expected to find element: `//p[text()='Success!']`, but never found it.","time":{"start":1668070889861,"stop":1668070905355,"duration":15494}}]},"346ee077b7d16fb1ec858423e9167051":{"statistic":{"failed":0,"broken":0,"skipped":0,"passed":1,"unknown":0,"total":1},"items":[{"uid":"ece9bdad3d038be9","reportUrl":"https://itdelta-agency.github.io/op3-cypress-tests/75//#testresult/ece9bdad3d038be9","status":"passed","time":{"start":1668071132616,"stop":1668071133455,"duration":839}}]},"40f6166aec22abfb8b291e1cd6bf716c":{"statistic":{"failed":0,"broken":0,"skipped":0,"passed":1,"unknown":0,"total":1},"items":[{"uid":"976b1e91c82039db","reportUrl":"https://itdelta-agency.github.io/op3-cypress-tests/75//#testresult/976b1e91c82039db","status":"passed","time":{"start":1668071113738,"stop":1668071119161,"duration":5423}}]}}